[
  {
    "id": "2218470047-1",
    "type": "PALLET",
    "order_id": "2218470047",
    "demand": 1,
    "pickup_factory_id": "f6faef4b36e743328800b961aced4a2c",
    "delivery_factory_id": "b6dd694ae05541dba369a2a759d2c2b9",
    "creation_time": 1621779527,
    "committed_completion_time": 1621707527,
    "load_time": 240,
    "unload_time": 240,
    "delivery_state": 2
  },
  {
    "id": "2218470047-2",
    "type": "PALLET",
    "order_id": "2218470047",
    "demand": 1,
    "pickup_factory_id": "f6faef4b36e743328800b961aced4a2c",
    "delivery_factory_id": "b6dd694ae05541dba369a2a759d2c2b9",
    "creation_time": 1621779527,
    "committed_completion_time": 1621707527,
    "load_time": 240,
    "unload_time": 240,
    "delivery_state": 2
  }
]